hyperconfig/__init__.py
hyperconfig-0.0.1.dist-info/METADATA
hyperconfig-0.0.1.dist-info/RECORD
hyperconfig-0.0.1.dist-info/WHEEL
hyperconfig-0.0.1.dist-info/top_level.txt
