Metadata-Version: 2.1
Name: hyperconfig
Version: 0.0.1
Summary: A high-level library to help using Pytorch
Home-page: https://github.com/walsvid/hyperconfig
Author: walsvid
Author-email: walsvid@gmail.com
License: MIT
Platform: UNKNOWN
Requires-Dist: torch
